MANIFEST.in
README.md
requirements-dev.txt
setup.py
mcutk/__init__.py
mcutk/__main__.py
mcutk/_version.py
mcutk/appbase.py
mcutk/board.py
mcutk/cmsis_pack.py
mcutk/elftool.py
mcutk/exceptions.py
mcutk/gdb_session.py
mcutk/projects_scanner.py
mcutk/pserial.py
mcutk/repo.py
mcutk/sdk_manifest.py
mcutk/shortcuts.py
mcutk/util.py
mcutk/apps/__init__.py
mcutk/apps/decorators.py
mcutk/apps/eclipse.py
mcutk/apps/idebase.py
mcutk/apps/projectbase.py
mcutk/apps/armgcc/__init__.py
mcutk/apps/armgcc/app.py
mcutk/apps/armgcc/project.py
mcutk/apps/cmake/__init__.py
mcutk/apps/cmake/project.py
mcutk/apps/codewarrior/__init__.py
mcutk/apps/codewarrior/app.py
mcutk/apps/codewarrior/project.py
mcutk/apps/ds5/__init__.py
mcutk/apps/ds5/app.py
mcutk/apps/ds5/project.py
mcutk/apps/iar/__init__.py
mcutk/apps/iar/app.py
mcutk/apps/iar/project.py
mcutk/apps/kds/__init__.py
mcutk/apps/kds/app.py
mcutk/apps/kds/project.py
mcutk/apps/lpcx/__init__.py
mcutk/apps/lpcx/app.py
mcutk/apps/lpcx/project.py
mcutk/apps/mcux/__init__.py
mcutk/apps/mcux/app.py
mcutk/apps/mcux/project.py
mcutk/apps/mdk/__init__.py
mcutk/apps/mdk/app.py
mcutk/apps/mdk/project.py
mcutk/apps/xcc/__init__.py
mcutk/apps/xcc/app.py
mcutk/apps/xcc/project.py
mcutk/commands/__init__.py
mcutk/commands/build.py
mcutk/commands/config.py
mcutk/commands/flash.py
mcutk/commands/gdbserver.py
mcutk/commands/scan.py
mcutk/debugger/__init__.py
mcutk/debugger/blhost.py
mcutk/debugger/general.py
mcutk/debugger/ide.py
mcutk/debugger/jlink.py
mcutk/debugger/pyocd.py
mcutk/debugger/redlink.py
mcutk/managers/__init__.py
mcutk/managers/conf_mgr.py
mcutk/managers/debug_helper.py
mcutk/spawns/__init__.py
mcutk/spawns/base.py
mcutk/spawns/rttspawn.py
mcutk/spawns/serialspawn.py
pymcutk.egg-info/PKG-INFO
pymcutk.egg-info/SOURCES.txt
pymcutk.egg-info/dependency_links.txt
pymcutk.egg-info/entry_points.txt
pymcutk.egg-info/requires.txt
pymcutk.egg-info/top_level.txt