Metadata-Version: 2.1
Name: pymcutk
Version: 0.3.4
Summary: A lite tool kit for MCU.
Home-page: https://github.com/Hoohaha/pymcutk
Author: Haley Guo, Fly Yu
License: MIT License
Platform: UNKNOWN
Classifier: Development Status :: 4 - Beta
Classifier: Programming Language :: Python
Classifier: Programming Language :: Python :: 3.6
Classifier: Programming Language :: Python :: 3.7
Classifier: Programming Language :: Python :: 3.8
Provides-Extra: pyocd
